isbnlib_loc/__init__.py
isbnlib_loc/_loc.py
isbnlib_loc-1.0.2.dist-info/LICENSE-LGPL.txt
isbnlib_loc-1.0.2.dist-info/METADATA
isbnlib_loc-1.0.2.dist-info/WHEEL
isbnlib_loc-1.0.2.dist-info/entry_points.txt
isbnlib_loc-1.0.2.dist-info/top_level.txt
isbnlib_loc-1.0.2.dist-info/RECORD
